countrycode/__init__.py
countrycode/countrycode.py
countrycode/data/codelist.pickle
countrycode-0.6.0.dist-info/licenses/LICENSE
countrycode-0.6.0.dist-info/METADATA
countrycode-0.6.0.dist-info/WHEEL
countrycode-0.6.0.dist-info/top_level.txt
countrycode-0.6.0.dist-info/RECORD
