Metadata-Version: 2.4
Name: countrycode
Version: 0.6.0
Summary: Convert country names and country codes
Author-email: Vincent Arel-Bundock <vincent.arel-bundock@umontreal.ca>
License-Expression: GPL-3.0-or-later
Project-URL: Repository, https://github.com/vincentarelbundock/pycountrycode
Project-URL: Readme, https://github.com/vincentarelbundock/pycountrycode/blob/main/README.md
Project-URL: Changelog, https://github.com/vincentarelbundock/pycountrycode/blob/main/NEWS.md
Requires-Python: >=3.9
License-File: LICENSE
Provides-Extra: pandas
Requires-Dist: pandas>=2.0.0; extra == "pandas"
Provides-Extra: polars
Requires-Dist: polars>=1.0.0; extra == "polars"
Provides-Extra: full
Requires-Dist: pandas>=2.0.0; extra == "full"
Requires-Dist: polars>=1.0.0; extra == "full"
Dynamic: license-file
